AUTHORS
CHANGELOG.txt
DESCRIPTION
LICENSE
MANIFEST.in
README.rst
setup.cfg
setup.py
cmsplugin_template_placeholder/__init__.py
cmsplugin_template_placeholder/models.py
cmsplugin_template_placeholder.egg-info/PKG-INFO
cmsplugin_template_placeholder.egg-info/SOURCES.txt
cmsplugin_template_placeholder.egg-info/dependency_links.txt
cmsplugin_template_placeholder.egg-info/requires.txt
cmsplugin_template_placeholder.egg-info/top_level.txt
cmsplugin_template_placeholder/templatetags/__init__.py
cmsplugin_template_placeholder/templatetags/cmsplugin_template_placeholder_tags.py
cmsplugin_template_placeholder/tests/.coverage
cmsplugin_template_placeholder/tests/.coveragerc
cmsplugin_template_placeholder/tests/__init__.py
cmsplugin_template_placeholder/tests/runtests.py
cmsplugin_template_placeholder/tests/south_settings.py
cmsplugin_template_placeholder/tests/test_settings.py
cmsplugin_template_placeholder/tests/urls.py