Metadata-Version: 1.0
Name: cmsplugin-template-placeholder
Version: 0.1
Summary: A django-cms plugin with a better placeholder tag.
